[
  {
    "line": 2,
    "elements": [
      {
        "line": 5,
        "name": "Sunday isn\u0027t Friday",
        "description": "",
        "id": "is-it-friday-yet?;sunday-isn-t-friday",
        "type": "scenario",
        "keyword": "Scenario",
        "steps": [
          {
            "result": {
              "duration": 5121943257,
              "status": "passed"
            },
            "line": 6,
            "name": "today is Sunday",
            "match": {
              "location": "googlesteps.today_is_Sunday()"
            },
            "after": [
              {
                "result": {
                  "duration": 4061090,
                  "status": "passed"
                },
                "match": {
                  "location": "hooks.handlefailure(Scenario)"
                }
              }
            ],
            "keyword": "Given "
          },
          {
            "result": {
              "duration": 22449437106,
              "status": "passed"
            },
            "line": 7,
            "name": "I ask whether it\u0027s Friday yet",
            "match": {
              "location": "googlesteps.i_ask_whether_it_s_Friday_yet()"
            },
            "after": [
              {
                "result": {
                  "duration": 320653,
                  "status": "passed"
                },
                "match": {
                  "location": "hooks.handlefailure(Scenario)"
                }
              }
            ],
            "keyword": "When "
          },
          {
            "result": {
              "duration": 203024470,
              "status": "passed"
            },
            "line": 8,
            "name": "I should be told \"Nope\"",
            "match": {
              "arguments": [
                {
                  "val": "\"Nope\"",
                  "offset": 17
                }
              ],
              "location": "googlesteps.i_should_be_told(String)"
            },
            "after": [
              {
                "result": {
                  "duration": 171151,
                  "status": "passed"
                },
                "match": {
                  "location": "hooks.handlefailure(Scenario)"
                }
              }
            ],
            "keyword": "Then "
          }
        ],
        "tags": [
          {
            "name": "@test"
          }
        ]
      }
    ],
    "name": "Is it Friday yet?",
    "description": "  Everybody wants to know when it\u0027s Friday",
    "id": "is-it-friday-yet?",
    "keyword": "Feature",
    "uri": "file:src/test/resources/features/google_search.feature",
    "tags": [
      {
        "name": "@test",
        "type": "Tag",
        "location": {
          "line": 1,
          "column": 1
        }
      }
    ]
  }
]